hlr_agent/__init__.py
hlr_agent/agent.py
hlr_agent/llm.py
hlr_agent/node.py
hlr_agent-0.3.0.dist-info/licenses/LICENSE
hlr_agent-0.3.0.dist-info/METADATA
hlr_agent-0.3.0.dist-info/WHEEL
hlr_agent-0.3.0.dist-info/top_level.txt
hlr_agent-0.3.0.dist-info/RECORD
