Metadata-Version: 2.4
Name: hlr_agent
Version: 0.3.0
Summary: A library for managing nodes and agent workflows
Author: David Serrano Díaz
Author-email: David Serrano <davidsd.2704@gmail.com>
License: Creative Commons Attribution-NonCommercial 4.0 International License
Project-URL: Homepage, https://github.com/DavidFraifer/HLR
Requires-Python: >=3.6
License-File: LICENSE
Requires-Dist: openai
Requires-Dist: google-genai
Dynamic: author
Dynamic: license-file
Dynamic: requires-python
